academic_community/__init__.py
academic_community/_version.py
academic_community/admin.py
academic_community/apps.py
academic_community/cms_plugins.py
academic_community/cms_toolbars.py
academic_community/context_processors.py
academic_community/decorators.py
academic_community/filters.py
academic_community/forms.py
academic_community/middleware.py
academic_community/mixins.py
academic_community/py.typed
academic_community/urls.py
academic_community/utils.py
academic_community/validators.py
academic_community/views.py
academic_community/activities/__init__.py
academic_community/activities/admin.py
academic_community/activities/apps.py
academic_community/activities/cms_plugins.py
academic_community/activities/filters.py
academic_community/activities/forms.py
academic_community/activities/models.py
academic_community/activities/urls.py
academic_community/activities/views.py
academic_community/activities/migrations/0001_initial.py
academic_community/activities/migrations/0002_auto_20210422_2140.py
academic_community/activities/migrations/0003_activity_former_members.py
academic_community/activities/migrations/0004_auto_20210424_1438.py
academic_community/activities/migrations/0005_category_abbreviation.py
academic_community/activities/migrations/0006_auto_20210522_1552.py
academic_community/activities/migrations/0007_auto_20210522_1928.py
academic_community/activities/migrations/0008_activity_groups.py
academic_community/activities/migrations/0009_remove_activity_mailing_list.py
academic_community/activities/migrations/0010_activitymaterial.py
academic_community/activities/migrations/0011_activity_leaders.py
academic_community/activities/migrations/0012_auto_20220824_1437.py
academic_community/activities/migrations/0013_activitymateriallistpluginmodel.py
academic_community/activities/migrations/0014_auto_20220919_1955.py
academic_community/activities/migrations/0015_activitychannelgroup_activitychannelrelation.py
django_academic_community-0.0.1.dev0.dist-info/LICENSE
django_academic_community-0.0.1.dev0.dist-info/METADATA
django_academic_community-0.0.1.dev0.dist-info/WHEEL
django_academic_community-0.0.1.dev0.dist-info/top_level.txt
django_academic_community-0.0.1.dev0.dist-info/RECORD
