Metadata-Version: 2.1
Name: django-academic-community
Version: 0.0.1.dev0
Summary: A Django app to manage members, topics and more in an academic community
Home-page: https://codebase.helmholtz.cloud/hcdc/django/clm-community/django-academic-community
Author: Phiilpp S. Sommer
Author-email: philipp.sommer@hereon.de
License: EUPL-1.2
Classifier: Development Status :: 3 - Alpha
Classifier: Environment :: Web Environment
Classifier: Framework :: Django
Classifier: Framework :: Django :: 3.2
Classifier: Intended Audience :: Developers
Classifier: License :: OSI Approved :: European Union Public Licence 1.2 (EUPL 1.2)
Classifier: Operating System :: OS Independent
Classifier: Programming Language :: Python
Classifier: Programming Language :: Python :: 3
Classifier: Programming Language :: Python :: 3 :: Only
Classifier: Programming Language :: Python :: 3.7
Classifier: Programming Language :: Python :: 3.8
Classifier: Programming Language :: Python :: 3.9
Classifier: Topic :: Internet :: WWW/HTTP
Classifier: Topic :: Internet :: WWW/HTTP :: Dynamic Content
Requires-Python: >=3.7
License-File: LICENSE
Requires-Dist: requests
Requires-Dist: Django (<3.3,>=3.1)
Requires-Dist: beautifulsoup4
Requires-Dist: django-select2
Requires-Dist: django-e2ee-framework
Requires-Dist: djangorestframework
Requires-Dist: django-phonenumber-field[phonenumberslite]
Requires-Dist: django-bootstrap5
Requires-Dist: django-reversion
Requires-Dist: django-reversion-compare
Requires-Dist: django-guardian
Requires-Dist: django-simple-captcha
Requires-Dist: django-colorfield
Requires-Dist: django-extensions
Requires-Dist: django-private-storage
Requires-Dist: django-filter
Requires-Dist: cssutils
Requires-Dist: pywebpush
Requires-Dist: django-reactive
Requires-Dist: django-extra-views
Requires-Dist: Pillow (>=3.0)
Requires-Dist: django-cms (<3.12,>=3.10)
Requires-Dist: html5lib (>=1.0.1)
Requires-Dist: six
Requires-Dist: channels
Requires-Dist: pytz
Requires-Dist: django-classy-tags (>=2.0)
Requires-Dist: django-sekizai (>=2.0)
Requires-Dist: django-mptt (>0.9)
Requires-Dist: djangocms-admin-style (<4.0,>=3.0)
Requires-Dist: django-treebeard (<5.0,>=4.0)
Requires-Dist: djangocms-text-ckeditor (<6.0,>=5.0)
Requires-Dist: djangocms-link (<4.0,>=3.0)
Requires-Dist: djangocms-icon (<3.0,>=2.0)
Requires-Dist: djangocms-style (<4.0,>=3.0)
Requires-Dist: djangocms-googlemap (<3.0,>=2.0)
Requires-Dist: djangocms-video (<4.0,>=3.0)
Requires-Dist: djangocms-file (<4.0,>=3.0)
Requires-Dist: djangocms-picture (<6.0,>=4.0)
Requires-Dist: djangocms-bootstrap5 (<1.0)
Provides-Extra: dev
Requires-Dist: tox ; extra == 'dev'
Requires-Dist: requests ; extra == 'dev'
Requires-Dist: types-requests ; extra == 'dev'
Requires-Dist: pytest ; extra == 'dev'
Requires-Dist: pytest-cov ; extra == 'dev'
Requires-Dist: pytest-lazy-fixture ; extra == 'dev'
Requires-Dist: pytest-django ; extra == 'dev'
Requires-Dist: isort (==5.9.3) ; extra == 'dev'
Requires-Dist: black (==22.3.0) ; extra == 'dev'
Requires-Dist: blackdoc (==0.3.4) ; extra == 'dev'
Requires-Dist: flake8 (==6.0.0) ; extra == 'dev'
Requires-Dist: pre-commit ; extra == 'dev'
Requires-Dist: mypy ; extra == 'dev'
Requires-Dist: django-stubs (<1.12.0) ; extra == 'dev'
Requires-Dist: psycopg2-binary ; extra == 'dev'
Requires-Dist: sphinx ; extra == 'dev'
Requires-Dist: sphinxcontrib-django ; extra == 'dev'
Provides-Extra: testsite
Requires-Dist: tox ; extra == 'testsite'
Requires-Dist: requests ; extra == 'testsite'
Requires-Dist: types-requests ; extra == 'testsite'
Requires-Dist: pytest ; extra == 'testsite'
Requires-Dist: pytest-cov ; extra == 'testsite'
Requires-Dist: pytest-lazy-fixture ; extra == 'testsite'
Requires-Dist: pytest-django ; extra == 'testsite'
Requires-Dist: isort (==5.9.3) ; extra == 'testsite'
Requires-Dist: black (==22.3.0) ; extra == 'testsite'
Requires-Dist: blackdoc (==0.3.4) ; extra == 'testsite'
Requires-Dist: flake8 (==6.0.0) ; extra == 'testsite'
Requires-Dist: pre-commit ; extra == 'testsite'
Requires-Dist: mypy ; extra == 'testsite'
Requires-Dist: django-stubs (<1.12.0) ; extra == 'testsite'
Requires-Dist: psycopg2-binary ; extra == 'testsite'
